LICENSE
MANIFEST.in
README.txt
setup.py
atomisator/__init__.py
atomisator.main.egg-info/PKG-INFO
atomisator.main.egg-info/SOURCES.txt
atomisator.main.egg-info/dependency_links.txt
atomisator.main.egg-info/entry_points.txt
atomisator.main.egg-info/namespace_packages.txt
atomisator.main.egg-info/not-zip-safe
atomisator.main.egg-info/requires.txt
atomisator.main.egg-info/top_level.txt
atomisator/main/__init__.py
atomisator/main/atomisator.cfg
atomisator/main/atomisator.cfg_tmpl
atomisator/main/commands.py
atomisator/main/config.py
atomisator/main/core.py
atomisator/main/docs/README.txt
atomisator/main/docs/config.txt
atomisator/main/tests/__init__.py
atomisator/main/tests/atomisator.cfg_tmpl
atomisator/main/tests/base.py
atomisator/main/tests/buzzwords.txt
atomisator/main/tests/stopwords.txt
atomisator/main/tests/test.cfg
atomisator/main/tests/test2.cfg
atomisator/main/tests/test_commands.py
atomisator/main/tests/test_config.py
atomisator/main/tests/test_docs.py
atomisator/main/tests/test_main.py