Metadata-Version: 1.0
Name: atomisator.main
Version: 0.5.2
Summary: Expert Python Programming - Main package for Atomisator app
Home-page: http://atomisator.ziade.org
Author: Tarek Ziade
Author-email: tarek@ziade.org
License: GPL
Platform: UNKNOWN
Classifier: Programming Language :: Python
Classifier: Topic :: Software Development :: Libraries :: Python Modules
